emuserema/__init__.py
emuserema/__main__.py
emuserema/emuserema.py
emuserema/plugin_manager.py
emuserema/redirects.py
emuserema/services.py
emuserema/utils.py
emuserema/world.py
emuserema/yamlloader.py
emuserema/plugins/renderers/jstree.py
emuserema/plugins/renderers/mstsc.py
emuserema/plugins/renderers/openssh.py
emuserema/plugins/renderers/putty.py
emuserema/plugins/renderers/realvnc.py
emuserema/plugins/renderers/wssh_commands.py
emuserema/templates/jstree/jstree-html-postfix.html
emuserema/templates/jstree/jstree-html-prefix.html
emuserema/templates/openssh/openssh.j2
emuserema/templates/openssh/ssh_config_postfix
emuserema/templates/openssh/ssh_config_prefix
emuserema-0.2.3.data/scripts/viemuserema
emuserema-0.2.3.dist-info/LICENSE.txt
emuserema-0.2.3.dist-info/METADATA
emuserema-0.2.3.dist-info/WHEEL
emuserema-0.2.3.dist-info/entry_points.txt
emuserema-0.2.3.dist-info/top_level.txt
emuserema-0.2.3.dist-info/RECORD
